Metadata-Version: 1.0
Name: stestvtestdistributions
Version: 2.0
Summary: Gaussian and Binomial distributions
Home-page: UNKNOWN
Author: Swathi
Author-email: UNKNOWN
License: UNKNOWN
Platform: UNKNOWN
